{"name": "afterburner", "type": "colstag", "type_label": "Column-stagger", "keys": [{"char": ",", "freq": 0.0, "index": 1, "row": 0, "col": 1, "finger": 0, "finger_name": "LP", "finger_long": "Left Pinky", "hand": "L", "x": 1.0, "y": 0.35}, {"char": "u", "freq": 0.02679, "index": 2, "row": 0, "col": 2, "finger": 1, "finger_name": "LR", "finger_long": "Left Ring", "hand": "L", "x": 2.0, "y": 0.1}, {"char": "o", "freq": 0.07971, "index": 3, "row": 0, "col": 3, "finger": 2, "finger_name": "LM", "finger_long": "Left Middle", "hand": "L", "x": 3.0, "y": 0.0}, {"char": "c", "freq": 0.03343, "index": 4, "row": 0, "col": 4, "finger": 3, "finger_name": "LI", "finger_long": "Left Index", "hand": "L", "x": 4.0, "y": 0.1}, {"char": "z", "freq": 0.00071, "index": 5, "row": 0, "col": 5, "finger": 3, "finger_name": "LI", "finger_long": "Left Index", "hand": "L", "x": 5.0, "y": 0.2}, {"char": "k", "freq": 0.0063, "index": 6, "row": 0, "col": 6, "finger": 6, "finger_name": "RI", "finger_long": "Right Index", "hand": "R", "x": 6.0, "y": 0.2}, {"char": "d", "freq": 0.03484, "index": 7, "row": 0, "col": 7, "finger": 6, "finger_name": "RI", "finger_long": "Right Index", "hand": "R", "x": 7.0, "y": 0.1}, {"char": "g", "freq": 0.01832, "index": 8, "row": 0, "col": 8, "finger": 7, "finger_name": "RM", "finger_long": "Right Middle", "hand": "R", "x": 8.0, "y": 0.0}, {"char": "b", "freq": 0.01626, "index": 9, "row": 0, "col": 9, "finger": 8, "finger_name": "RR", "finger_long": "Right Ring", "hand": "R", "x": 9.0, "y": 0.1}, {"char": "j", "freq": 0.00169, "index": 10, "row": 0, "col": 10, "finger": 9, "finger_name": "RP", "finger_long": "Right Pinky", "hand": "R", "x": 10.0, "y": 0.35}, {"char": "i", "freq": 0.07505, "index": 13, "row": 1, "col": 1, "finger": 0, "finger_name": "LP", "finger_long": "Left Pinky", "hand": "L", "x": 1.0, "y": 1.35}, {"char": "e", "freq": 0.12435, "index": 14, "row": 1, "col": 2, "finger": 1, "finger_name": "LR", "finger_long": "Left Ring", "hand": "L", "x": 2.0, "y": 1.1}, {"char": "a", "freq": 0.07959, "index": 15, "row": 1, "col": 3, "finger": 2, "finger_name": "LM", "finger_long": "Left Middle", "hand": "L", "x": 3.0, "y": 1.0}, {"char": "$", "freq": 0.0, "index": 16, "row": 1, "col": 4, "finger": 3, "finger_name": "LI", "finger_long": "Left Index", "hand": "L", "x": 4.0, "y": 1.1}, {"char": "#", "freq": 0.0, "index": 17, "row": 1, "col": 5, "finger": 3, "finger_name": "LI", "finger_long": "Left Index", "hand": "L", "x": 5.0, "y": 1.2}, {"char": "m", "freq": 0.02439, "index": 18, "row": 1, "col": 6, "finger": 6, "finger_name": "RI", "finger_long": "Right Index", "hand": "R", "x": 6.0, "y": 1.2}, {"char": "t", "freq": 0.09349, "index": 19, "row": 1, "col": 7, "finger": 6, "finger_name": "RI", "finger_long": "Right Index", "hand": "R", "x": 7.0, "y": 1.1}, {"char": "s", "freq": 0.06417, "index": 20, "row": 1, "col": 8, "finger": 7, "finger_name": "RM", "finger_long": "Right Middle", "hand": "R", "x": 8.0, "y": 1.0}, {"char": "n", "freq": 0.0692, "index": 21, "row": 1, "col": 9, "finger": 8, "finger_name": "RR", "finger_long": "Right Ring", "hand": "R", "x": 9.0, "y": 1.1}, {"char": "h", "freq": 0.05327, "index": 22, "row": 1, "col": 10, "finger": 9, "finger_name": "RP", "finger_long": "Right Pinky", "hand": "R", "x": 10.0, "y": 1.35}, {"char": "q", "freq": 0.00086, "index": 23, "row": 1, "col": 11, "finger": 9, "finger_name": "RP", "finger_long": "Right Pinky", "hand": "R", "x": 11.0, "y": 1.35}, {"char": ".", "freq": 0.0, "index": 25, "row": 2, "col": 1, "finger": 0, "finger_name": "LP", "finger_long": "Left Pinky", "hand": "L", "x": 1.0, "y": 2.35}, {"char": ";", "freq": 0.0, "index": 26, "row": 2, "col": 2, "finger": 1, "finger_name": "LR", "finger_long": "Left Ring", "hand": "L", "x": 2.0, "y": 2.1}, {"char": "/", "freq": 0.0, "index": 27, "row": 2, "col": 3, "finger": 2, "finger_name": "LM", "finger_long": "Left Middle", "hand": "L", "x": 3.0, "y": 2.0}, {"char": "w", "freq": 0.01637, "index": 28, "row": 2, "col": 4, "finger": 3, "finger_name": "LI", "finger_long": "Left Index", "hand": "L", "x": 4.0, "y": 2.1}, {"char": "'", "freq": 0.0, "index": 29, "row": 2, "col": 5, "finger": 3, "finger_name": "LI", "finger_long": "Left Index", "hand": "L", "x": 5.0, "y": 2.2}, {"char": "x", "freq": 0.00212, "index": 30, "row": 2, "col": 6, "finger": 6, "finger_name": "RI", "finger_long": "Right Index", "hand": "R", "x": 6.0, "y": 2.2}, {"char": "v", "freq": 0.01012, "index": 31, "row": 2, "col": 7, "finger": 6, "finger_name": "RI", "finger_long": "Right Index", "hand": "R", "x": 7.0, "y": 2.1}, {"char": "f", "freq": 0.02824, "index": 32, "row": 2, "col": 8, "finger": 7, "finger_name": "RM", "finger_long": "Right Middle", "hand": "R", "x": 8.0, "y": 2.0}, {"char": "p", "freq": 0.02272, "index": 33, "row": 2, "col": 9, "finger": 8, "finger_name": "RR", "finger_long": "Right Ring", "hand": "R", "x": 9.0, "y": 2.1}, {"char": "y", "freq": 0.01801, "index": 34, "row": 2, "col": 10, "finger": 9, "finger_name": "RP", "finger_long": "Right Pinky", "hand": "R", "x": 10.0, "y": 2.35}, {"char": "space", "freq": 0.0, "index": 38, "row": 3, "col": 2, "finger": 4, "finger_name": "LT", "finger_long": "Left Thumb", "hand": "L", "x": 2.0, "y": 3.0}, {"char": "l", "freq": 0.03728, "index": 39, "row": 3, "col": 3, "finger": 5, "finger_name": "RT", "finger_long": "Right Thumb", "hand": "R", "x": 3.0, "y": 3.0}, {"char": "r", "freq": 0.06273, "index": 40, "row": 3, "col": 4, "finger": 5, "finger_name": "RT", "finger_long": "Right Thumb", "hand": "R", "x": 4.0, "y": 3.0}], "key_unit_mm": 19.05, "corpora": {"english_1k": {"wpm": 155.5309, "mean_iki_ms": 77.1558, "total_ms": 8172420.6629, "chars": 105922, "skipped": 0, "travel_mm_per_char": 6.9504, "sfb_time_share": 0.001, "sfb": 0.0015, "sfs": 0.032, "alternation": 0.6853, "same_hand": 0.3147, "roll_in": 0.0813, "roll_out": 0.1674, "roll_total": 0.2487, "lateral_stretch": 0.001, "redirect": 0.0142, "tri_roll": 0.0092, "tri_alternation": 0.3747, "in_out_ratio": 0.4859, "finger_load": [0.0555, 0.1593, 0.1769, 0.0472, 0.0, 0.0845, 0.1887, 0.0936, 0.0868, 0.1075], "row_load": [0.2109, 0.602, 0.1025, 0.0845], "hand_load": [0.4389, 0.5611], "pinky_load": 0.163, "home_row": 0.602}, "english_5k": {"wpm": 157.2217, "mean_iki_ms": 76.3259, "total_ms": 9727894.9386, "chars": 127453, "skipped": 0, "travel_mm_per_char": 7.7818, "sfb_time_share": 0.0029, "sfb": 0.0046, "sfs": 0.0454, "alternation": 0.6809, "same_hand": 0.3191, "roll_in": 0.1057, "roll_out": 0.134, "roll_total": 0.2396, "lateral_stretch": 0.003, "redirect": 0.0223, "tri_roll": 0.0067, "tri_alternation": 0.4093, "in_out_ratio": 0.7887, "finger_load": [0.0712, 0.1529, 0.1617, 0.0503, 0.0, 0.0986, 0.1724, 0.1094, 0.106, 0.0775], "row_load": [0.2158, 0.5858, 0.0999, 0.0986], "hand_load": [0.4361, 0.5639], "pinky_load": 0.1487, "home_row": 0.5858}, "english_10k": {"wpm": 157.6126, "mean_iki_ms": 76.1358, "total_ms": 10139263.6505, "chars": 133173, "skipped": 0, "travel_mm_per_char": 7.8949, "sfb_time_share": 0.0031, "sfb": 0.005, "sfs": 0.0459, "alternation": 0.6819, "same_hand": 0.3181, "roll_in": 0.1086, "roll_out": 0.128, "roll_total": 0.2366, "lateral_stretch": 0.0033, "redirect": 0.0241, "tri_roll": 0.0062, "tri_alternation": 0.4149, "in_out_ratio": 0.8481, "finger_load": [0.075, 0.1511, 0.1593, 0.0505, 0.0, 0.1, 0.1713, 0.1107, 0.1082, 0.0738], "row_load": [0.218, 0.5844, 0.0976, 0.1], "hand_load": [0.436, 0.564], "pinky_load": 0.1489, "home_row": 0.5844}}, "keycraft": {"#": 9.0, "Score": 22.33, "SFB": 0.59, "LSB": 0.34, "FSB": 0.16, "HSB": 4.41, "SFS": 4.81, "LSS": 1.36, "FSS": 0.47, "HSS": 3.8, "RED": 3.15, "RED-NML": 2.72, "RED-WEAK": 0.18, "RED-SFS": 0.25, "ALT": 41.0, "ALT-NML": 36.53, "ALT-SFS": 4.47, "2RL": 50.72, "2RL-IN": 21.51, "2RL-OUT": 22.65, "2RL-SFB": 6.56, "3RL": 2.68, "3RL-IN": 0.5, "3RL-OUT": 0.88, "3RL-SFB": 1.3, "FLW": 82.08, "IN:OUT": 0.94, "HLD": 0.78, "FLD": 31.13, "RLD": 26.23, "POH": 8.16, "H0": 49.61, "H1": 50.39, "F0": 10.38, "F1": 16.08, "F2": 17.19, "F3": 5.96, "F4": 0.0, "F5": 0.0, "F6": 19.32, "F7": 11.48, "F8": 11.17, "F9": 8.43, "R0": 25.19, "R1": 61.89, "R2": 12.92, "R3": 10.38, "C0": 0.0, "C1": 10.38, "C2": 16.08, "C3": 17.19, "C4": 5.02, "C5": 0.93, "C6": 4.05, "C7": 15.27, "C8": 11.48, "C9": 11.17, "C10": 8.34, "C11": 0.09}}