{"name": "colemak-dh", "type": "rowstag", "type_label": "Row-stagger", "keys": [{"char": "q", "freq": 0.00086, "index": 1, "row": 0, "col": 1, "finger": 0, "finger_name": "LP", "finger_long": "Left Pinky", "hand": "L", "x": 1.0, "y": 0.0}, {"char": "w", "freq": 0.01637, "index": 2, "row": 0, "col": 2, "finger": 1, "finger_name": "LR", "finger_long": "Left Ring", "hand": "L", "x": 2.0, "y": 0.0}, {"char": "f", "freq": 0.02824, "index": 3, "row": 0, "col": 3, "finger": 2, "finger_name": "LM", "finger_long": "Left Middle", "hand": "L", "x": 3.0, "y": 0.0}, {"char": "p", "freq": 0.02272, "index": 4, "row": 0, "col": 4, "finger": 3, "finger_name": "LI", "finger_long": "Left Index", "hand": "L", "x": 4.0, "y": 0.0}, {"char": "b", "freq": 0.01626, "index": 5, "row": 0, "col": 5, "finger": 3, "finger_name": "LI", "finger_long": "Left Index", "hand": "L", "x": 5.0, "y": 0.0}, {"char": "j", "freq": 0.00169, "index": 6, "row": 0, "col": 6, "finger": 6, "finger_name": "RI", "finger_long": "Right Index", "hand": "R", "x": 6.0, "y": 0.0}, {"char": "l", "freq": 0.03728, "index": 7, "row": 0, "col": 7, "finger": 6, "finger_name": "RI", "finger_long": "Right Index", "hand": "R", "x": 7.0, "y": 0.0}, {"char": "u", "freq": 0.02679, "index": 8, "row": 0, "col": 8, "finger": 7, "finger_name": "RM", "finger_long": "Right Middle", "hand": "R", "x": 8.0, "y": 0.0}, {"char": "y", "freq": 0.01801, "index": 9, "row": 0, "col": 9, "finger": 8, "finger_name": "RR", "finger_long": "Right Ring", "hand": "R", "x": 9.0, "y": 0.0}, {"char": ";", "freq": 0.0, "index": 10, "row": 0, "col": 10, "finger": 9, "finger_name": "RP", "finger_long": "Right Pinky", "hand": "R", "x": 10.0, "y": 0.0}, {"char": "a", "freq": 0.07959, "index": 13, "row": 1, "col": 1, "finger": 0, "finger_name": "LP", "finger_long": "Left Pinky", "hand": "L", "x": 1.25, "y": 1.0}, {"char": "r", "freq": 0.06273, "index": 14, "row": 1, "col": 2, "finger": 1, "finger_name": "LR", "finger_long": "Left Ring", "hand": "L", "x": 2.25, "y": 1.0}, {"char": "s", "freq": 0.06417, "index": 15, "row": 1, "col": 3, "finger": 2, "finger_name": "LM", "finger_long": "Left Middle", "hand": "L", "x": 3.25, "y": 1.0}, {"char": "t", "freq": 0.09349, "index": 16, "row": 1, "col": 4, "finger": 3, "finger_name": "LI", "finger_long": "Left Index", "hand": "L", "x": 4.25, "y": 1.0}, {"char": "g", "freq": 0.01832, "index": 17, "row": 1, "col": 5, "finger": 3, "finger_name": "LI", "finger_long": "Left Index", "hand": "L", "x": 5.25, "y": 1.0}, {"char": "m", "freq": 0.02439, "index": 18, "row": 1, "col": 6, "finger": 6, "finger_name": "RI", "finger_long": "Right Index", "hand": "R", "x": 6.25, "y": 1.0}, {"char": "n", "freq": 0.0692, "index": 19, "row": 1, "col": 7, "finger": 6, "finger_name": "RI", "finger_long": "Right Index", "hand": "R", "x": 7.25, "y": 1.0}, {"char": "e", "freq": 0.12435, "index": 20, "row": 1, "col": 8, "finger": 7, "finger_name": "RM", "finger_long": "Right Middle", "hand": "R", "x": 8.25, "y": 1.0}, {"char": "i", "freq": 0.07505, "index": 21, "row": 1, "col": 9, "finger": 8, "finger_name": "RR", "finger_long": "Right Ring", "hand": "R", "x": 9.25, "y": 1.0}, {"char": "o", "freq": 0.07971, "index": 22, "row": 1, "col": 10, "finger": 9, "finger_name": "RP", "finger_long": "Right Pinky", "hand": "R", "x": 10.25, "y": 1.0}, {"char": "z", "freq": 0.00071, "index": 25, "row": 2, "col": 1, "finger": 0, "finger_name": "LP", "finger_long": "Left Pinky", "hand": "L", "x": 1.75, "y": 2.0}, {"char": "x", "freq": 0.00212, "index": 26, "row": 2, "col": 2, "finger": 1, "finger_name": "LR", "finger_long": "Left Ring", "hand": "L", "x": 2.75, "y": 2.0}, {"char": "c", "freq": 0.03343, "index": 27, "row": 2, "col": 3, "finger": 2, "finger_name": "LM", "finger_long": "Left Middle", "hand": "L", "x": 3.75, "y": 2.0}, {"char": "d", "freq": 0.03484, "index": 28, "row": 2, "col": 4, "finger": 3, "finger_name": "LI", "finger_long": "Left Index", "hand": "L", "x": 4.75, "y": 2.0}, {"char": "v", "freq": 0.01012, "index": 29, "row": 2, "col": 5, "finger": 3, "finger_name": "LI", "finger_long": "Left Index", "hand": "L", "x": 5.75, "y": 2.0}, {"char": "k", "freq": 0.0063, "index": 30, "row": 2, "col": 6, "finger": 6, "finger_name": "RI", "finger_long": "Right Index", "hand": "R", "x": 6.75, "y": 2.0}, {"char": "h", "freq": 0.05327, "index": 31, "row": 2, "col": 7, "finger": 6, "finger_name": "RI", "finger_long": "Right Index", "hand": "R", "x": 7.75, "y": 2.0}, {"char": ",", "freq": 0.0, "index": 32, "row": 2, "col": 8, "finger": 7, "finger_name": "RM", "finger_long": "Right Middle", "hand": "R", "x": 8.75, "y": 2.0}, {"char": ".", "freq": 0.0, "index": 33, "row": 2, "col": 9, "finger": 8, "finger_name": "RR", "finger_long": "Right Ring", "hand": "R", "x": 9.75, "y": 2.0}, {"char": "/", "freq": 0.0, "index": 34, "row": 2, "col": 10, "finger": 9, "finger_name": "RP", "finger_long": "Right Pinky", "hand": "R", "x": 10.75, "y": 2.0}, {"char": "space", "freq": 0.0, "index": 39, "row": 3, "col": 3, "finger": 5, "finger_name": "RT", "finger_long": "Right Thumb", "hand": "R", "x": 3.0, "y": 3.0}], "key_unit_mm": 19.05, "corpora": {"english_1k": {"wpm": 154.9055, "mean_iki_ms": 77.4673, "total_ms": 8205414.1142, "chars": 105922, "skipped": 0, "travel_mm_per_char": 7.9867, "sfb_time_share": 0.0024, "sfb": 0.0053, "sfs": 0.0837, "alternation": 0.5877, "same_hand": 0.4123, "roll_in": 0.1775, "roll_out": 0.2067, "roll_total": 0.3843, "lateral_stretch": 0.0113, "redirect": 0.1047, "tri_roll": 0.0298, "tri_alternation": 0.2889, "in_out_ratio": 0.8589, "finger_load": [0.0813, 0.0799, 0.1006, 0.2004, 0.0, 0.0, 0.2076, 0.1593, 0.0745, 0.0964], "row_load": [0.168, 0.6755, 0.1564, 0.0], "hand_load": [0.4622, 0.5378], "pinky_load": 0.1777, "home_row": 0.6755}, "english_5k": {"wpm": 156.4087, "mean_iki_ms": 76.7218, "total_ms": 9778457.0478, "chars": 127453, "skipped": 0, "travel_mm_per_char": 8.8319, "sfb_time_share": 0.0053, "sfb": 0.0098, "sfs": 0.081, "alternation": 0.5924, "same_hand": 0.4076, "roll_in": 0.1893, "roll_out": 0.1847, "roll_total": 0.374, "lateral_stretch": 0.0157, "redirect": 0.1012, "tri_roll": 0.0221, "tri_alternation": 0.3141, "in_out_ratio": 1.0246, "finger_load": [0.0815, 0.0806, 0.1251, 0.1949, 0.0, 0.0, 0.1937, 0.1529, 0.0899, 0.0815], "row_load": [0.1699, 0.6882, 0.1419, 0.0], "hand_load": [0.482, 0.518], "pinky_load": 0.163, "home_row": 0.6882}, "english_10k": {"wpm": 156.7502, "mean_iki_ms": 76.5555, "total_ms": 10195049.8451, "chars": 133173, "skipped": 0, "travel_mm_per_char": 8.9561, "sfb_time_share": 0.0055, "sfb": 0.01, "sfs": 0.0796, "alternation": 0.5901, "same_hand": 0.4099, "roll_in": 0.1918, "roll_out": 0.1836, "roll_total": 0.3754, "lateral_stretch": 0.0161, "redirect": 0.103, "tri_roll": 0.023, "tri_alternation": 0.3135, "in_out_ratio": 1.0446, "finger_load": [0.0812, 0.0812, 0.1258, 0.1958, 0.0, 0.0, 0.1921, 0.1511, 0.0931, 0.0797], "row_load": [0.1682, 0.691, 0.1408, 0.0], "hand_load": [0.484, 0.516], "pinky_load": 0.1609, "home_row": 0.691}}, "keycraft": {"#": 141.0, "Score": -53.76, "SFB": 1.41, "LSB": 1.57, "FSB": 0.27, "HSB": 5.47, "SFS": 8.42, "LSS": 1.37, "FSS": 0.81, "HSS": 5.57, "RED": 10.71, "RED-NML": 5.93, "RED-WEAK": 1.82, "RED-SFS": 2.96, "ALT": 28.11, "ALT-NML": 22.96, "ALT-SFS": 5.15, "2RL": 49.53, "2RL-IN": 23.63, "2RL-OUT": 20.56, "2RL-SFB": 5.34, "3RL": 6.63, "3RL-IN": 1.59, "3RL-OUT": 1.02, "3RL-SFB": 4.02, "FLW": 69.76, "IN:OUT": 1.17, "HLD": 7.76, "FLD": 16.36, "RLD": 16.46, "POH": 0.37, "H0": 46.12, "H1": 53.88, "F0": 8.02, "F1": 7.47, "F2": 10.89, "F3": 19.75, "F4": 0.0, "F5": 0.0, "F6": 19.42, "F7": 15.47, "F8": 11.13, "F9": 7.86, "R0": 17.57, "R1": 66.77, "R2": 15.66, "R3": 0.0, "C0": 0.0, "C1": 8.02, "C2": 7.47, "C3": 10.89, "C4": 14.86, "C5": 4.89, "C6": 3.72, "C7": 15.7, "C8": 15.47, "C9": 11.13, "C10": 7.86, "C11": 0.0}}